carolina.cpython-312-x86_64-linux-gnu.so
dakota.py
carolina.libs/lib3po-7d571160.so
carolina.libs/libamplsolver-5e1694c4.so
carolina.libs/libapproxnn-8e7a9dcf.so
carolina.libs/libblas-357956a1.so.3.4.2
carolina.libs/libboost_atomic-5b6a305f.so.1.87.0
carolina.libs/libboost_container-9991264c.so.1.87.0
carolina.libs/libboost_filesystem-bd6fd8f6.so.1.87.0
carolina.libs/libboost_graph-e9bc3ec7.so.1.87.0
carolina.libs/libboost_program_options-855bc5f8.so.1.87.0
carolina.libs/libboost_python312-dfd19695.so.1.87.0
carolina.libs/libboost_regex-5fc283f3.so.1.87.0
carolina.libs/libboost_serialization-713f2649.so.1.87.0
carolina.libs/libboost_system-8f6d3dbc.so.1.87.0
carolina.libs/libcolin-e56737b6.so
carolina.libs/libconmin-f4cce04f.so
carolina.libs/libcport-9c6d852d.so
carolina.libs/libdakota_src-b87033fa.so
carolina.libs/libdakota_src_fortran-0dea4719.so
carolina.libs/libdakota_surrogates-c1751893.so
carolina.libs/libdakota_util-d03b00f8.so
carolina.libs/libddace-7cdcca59.so
carolina.libs/libdfftpack-055abbf8.so
carolina.libs/libdream-80a1e20a.so
carolina.libs/libeutils-e7b11f70.so
carolina.libs/libfsudace-f1fc2793.so
carolina.libs/libgfortran-040039e1.so.5.0.0
carolina.libs/libgfortran-91cc3cb1.so.3.0.0
carolina.libs/libhopspack-c9905861.so
carolina.libs/libinterfaces-2ee5c6e3.so
carolina.libs/libjega-5ba8a15e.so
carolina.libs/libjega_fe-6b337250.so
carolina.libs/liblapack-1ad85175.so.3.4.2
carolina.libs/liblhs-11625cf9.so
carolina.libs/liblhs_mod-3a3ca542.so
carolina.libs/liblhs_mods-74fde53e.so
carolina.libs/libmoga-1e344ee8.so
carolina.libs/libncsuopt-326ebedf.so
carolina.libs/libnidr-f7466f52.so
carolina.libs/libnomad-b4e0dcd7.so
carolina.libs/liboptpp-3d20df0a.so
carolina.libs/libpebbl-f8602f23.so
carolina.libs/libpecos_src-14be4f1f.so
carolina.libs/libpecos_util-71fa8145.so
carolina.libs/libpsuade-7b7a1c09.so
carolina.libs/libquadmath-96973f99.so.0.0.0
carolina.libs/libscolib-7fa6c86a.so
carolina-2.0.2.dist-info/METADATA
carolina-2.0.2.dist-info/WHEEL
carolina-2.0.2.dist-info/top_level.txt
carolina-2.0.2.dist-info/RECORD
carolina-2.0.2.dist-info/licenses/LICENSE
carolina-2.0.2.dist-info/licenses/NOTICE
