Metadata-Version: 2.4
Name: carolina
Version: 2.0.2
Summary: Python wrapper around Dakota
Author: National Renewable Energy Laboratory (NREL)
Author-email: Equinor ASA <fg_sib-scout@equinor.com>
License: Apache 2.0
Classifier: Intended Audience :: Science/Research
Classifier: Natural Language :: English
Classifier: License :: OSI Approved :: Apache Software License
Classifier: Operating System :: OS Independent
Classifier: Programming Language :: Python
Classifier: Programming Language :: Python :: 3.11
Classifier: Programming Language :: Python :: 3.12
Classifier: Programming Language :: Python :: 3.13
Requires-Python: >=3.11
License-File: LICENSE
License-File: NOTICE
Requires-Dist: numpy
Dynamic: license-file
Dynamic: requires-dist
